image_processing/__init__.py
image_processing/processing/__init__.py
image_processing/processing/combination.py
image_processing/processing/transformation.py
image_processing/utils/__init__.py
image_processing/utils/io.py
image_processing/utils/plot.py
meu_pacote_imagem_teste_2025_232434-0.0.1.dist-info/METADATA
meu_pacote_imagem_teste_2025_232434-0.0.1.dist-info/WHEEL
meu_pacote_imagem_teste_2025_232434-0.0.1.dist-info/top_level.txt
meu_pacote_imagem_teste_2025_232434-0.0.1.dist-info/RECORD
