Metadata-Version: 2.4
Name: meu-pacote-imagem-teste-2025-232434
Version: 0.0.1
Summary: Um pacote simples para processar imagens com Python
Home-page: https://github.com/vixnzin/image-processing-package
Author: Vicenzo
Requires-Python: >=3.8
Requires-Dist: matplotlib
Requires-Dist: numpy
Requires-Dist: scikit-image>=0.16.1
Dynamic: author
Dynamic: description
Dynamic: description-content-type
Dynamic: home-page
Dynamic: requires-dist
Dynamic: requires-python
Dynamic: summary
